inference_cli/__init__.py
inference_cli/benchmark.py
inference_cli/cloud.py
inference_cli/main.py
inference_cli/server.py
inference_cli/version.py
inference_cli/workflows.py
inference_cli/configs/bounding_boxes.yml
inference_cli/configs/bounding_boxes_tracing.yml
inference_cli/configs/masks.yml
inference_cli/configs/polygons.yml
inference_cli/lib/__init__.py
inference_cli/lib/benchmark_adapter.py
inference_cli/lib/cloud_adapter.py
inference_cli/lib/container_adapter.py
inference_cli/lib/env.py
inference_cli/lib/exceptions.py
inference_cli/lib/infer_adapter.py
inference_cli/lib/logger.py
inference_cli/lib/tunnel_adapter.py
inference_cli/lib/utils.py
inference_cli/lib/benchmark/__init__.py
inference_cli/lib/benchmark/api_speed.py
inference_cli/lib/benchmark/dataset.py
inference_cli/lib/benchmark/inference_models_speed.py
inference_cli/lib/benchmark/platform.py
inference_cli/lib/benchmark/python_package_speed.py
inference_cli/lib/benchmark/results_gathering.py
inference_cli/lib/roboflow_cloud/__init__.py
inference_cli/lib/roboflow_cloud/common.py
inference_cli/lib/roboflow_cloud/config.py
inference_cli/lib/roboflow_cloud/core.py
inference_cli/lib/roboflow_cloud/errors.py
inference_cli/lib/roboflow_cloud/batch_processing/__init__.py
inference_cli/lib/roboflow_cloud/batch_processing/api_operations.py
inference_cli/lib/roboflow_cloud/batch_processing/core.py
inference_cli/lib/roboflow_cloud/batch_processing/entities.py
inference_cli/lib/roboflow_cloud/data_staging/__init__.py
inference_cli/lib/roboflow_cloud/data_staging/api_operations.py
inference_cli/lib/roboflow_cloud/data_staging/core.py
inference_cli/lib/roboflow_cloud/data_staging/entities.py
inference_cli/lib/workflows/__init__.py
inference_cli/lib/workflows/common.py
inference_cli/lib/workflows/core.py
inference_cli/lib/workflows/entities.py
inference_cli/lib/workflows/local_image_adapter.py
inference_cli/lib/workflows/remote_image_adapter.py
inference_cli/lib/workflows/video_adapter.py
inference_cli-0.64.6.dist-info/licenses/LICENSE
inference_cli-0.64.6.dist-info/licenses/LICENSE.core
inference_sdk/__init__.py
inference_cli-0.64.6.dist-info/METADATA
inference_cli-0.64.6.dist-info/WHEEL
inference_cli-0.64.6.dist-info/entry_points.txt
inference_cli-0.64.6.dist-info/top_level.txt
inference_cli-0.64.6.dist-info/RECORD
