Metadata-Version: 2.4
Name: inference-cli
Version: 0.64.6
Summary: With no prior knowledge of machine learning or device-specific deployment, you can deploy a computer vision model to a range of devices and environments using Roboflow Inference CLI.
Home-page: https://github.com/roboflow/inference
Author: Roboflow
Author-email: help@roboflow.com
Classifier: Development Status :: 5 - Production/Stable
Classifier: Intended Audience :: Developers
Classifier: Intended Audience :: Education
Classifier: Intended Audience :: Science/Research
Classifier: License :: OSI Approved :: Apache Software License
Classifier: Programming Language :: Python :: 3
Classifier: Programming Language :: Python :: 3 :: Only
Classifier: Topic :: Software Development
Classifier: Topic :: Scientific/Engineering
Classifier: Topic :: Scientific/Engineering :: Artificial Intelligence
Classifier: Topic :: Scientific/Engineering :: Image Recognition
Classifier: Typing :: Typed
Classifier: Operating System :: OS Independent
Requires-Python: >=3.9,<3.13
License-File: LICENSE
License-File: LICENSE.core
Requires-Dist: requests<3.0.0,>=2.32.0
Requires-Dist: docker<8.0.0,>=7.0.0
Requires-Dist: click<8.2.0
Requires-Dist: typer<=0.16.0,>=0.9.0
Requires-Dist: rich<15.0.0,>=13.0.0
Requires-Dist: PyYAML~=6.0.0
Requires-Dist: supervision>=0.26
Requires-Dist: opencv-python<=4.10.0.84,>=4.8.1.78
Requires-Dist: tqdm<5.0.0,>=4.0.0
Requires-Dist: nvidia-ml-py<13.0.0
Requires-Dist: py-cpuinfo~=9.0.0
Requires-Dist: aiohttp<=3.10.11,>=3.9.0
Requires-Dist: backoff~=2.2.0
Requires-Dist: pandas<3.0.0,>=2.2.3
Requires-Dist: pybase64~=1.0.0
Requires-Dist: pydantic<2.12.0,>=2.8.0
Requires-Dist: requests<3.0.0,>=2.32.0
Requires-Dist: dataclasses-json~=0.6.0
Requires-Dist: opencv-python<=4.10.0.84,>=4.8.1.78
Requires-Dist: pillow<12.0,>=11.0
Requires-Dist: supervision>=0.26
Requires-Dist: numpy<2.4.0,>=2.0.0
Requires-Dist: aiohttp<=3.10.11,>=3.9.0
Requires-Dist: backoff~=2.2.0
Requires-Dist: py-cpuinfo~=9.0.0
Provides-Extra: cloud-deploy
Requires-Dist: skypilot[aws,gcp]==0.8.0; extra == "cloud-deploy"
Requires-Dist: cryptography>=43.0.1; extra == "cloud-deploy"
Provides-Extra: cloud-storage
Requires-Dist: fsspec<2025.0.0,>=2024.6.0; extra == "cloud-storage"
Requires-Dist: s3fs<2025.0.0,>=2024.6.0; extra == "cloud-storage"
Requires-Dist: gcsfs<2025.0.0,>=2024.6.0; extra == "cloud-storage"
Requires-Dist: adlfs<2025.0.0,>=2024.4.1; extra == "cloud-storage"
Dynamic: author
Dynamic: author-email
Dynamic: classifier
Dynamic: description
Dynamic: description-content-type
Dynamic: home-page
Dynamic: license-file
Dynamic: provides-extra
Dynamic: requires-dist
Dynamic: requires-python
Dynamic: summary
